vecstack/__init__.py
vecstack/core.py
vecstack/coresk.py
vecstack-0.5.1.dist-info/licenses/LICENSE.txt
vecstack-0.5.1.dist-info/METADATA
vecstack-0.5.1.dist-info/WHEEL
vecstack-0.5.1.dist-info/top_level.txt
vecstack-0.5.1.dist-info/RECORD
